LICENSE
MANIFEST.in
README.md
README.rst
setup.cfg
setup.py
pygrok/__init__.py
pygrok/pygrok.py
pygrok/patterns/aws
pygrok/patterns/bacula
pygrok/patterns/bro
pygrok/patterns/exim
pygrok/patterns/firewalls
pygrok/patterns/grok-patterns
pygrok/patterns/haproxy
pygrok/patterns/java
pygrok/patterns/junos
pygrok/patterns/linux-syslog
pygrok/patterns/mcollective
pygrok/patterns/mcollective-patterns
pygrok/patterns/mongodb
pygrok/patterns/nagios
pygrok/patterns/postgresql
pygrok/patterns/rails
pygrok/patterns/redis
pygrok/patterns/ruby
pygroker.egg-info/PKG-INFO
pygroker.egg-info/SOURCES.txt
pygroker.egg-info/dependency_links.txt
pygroker.egg-info/requires.txt
pygroker.egg-info/top_level.txt
tests/test_pygrok.py