Metadata-Version: 1.1
Name: pygroker
Version: 0.1.1
Summary: Temporary package for https://github.com/garyelephant/pygrok/pull/3
Home-page: https://github.com/garyelephant/pygrok
Author: garyelephant
Author-email: garygaowork@gmail.com
License: MIT
Download-URL: https://github.com/garyelephant/pygrok/tarball/v0.7.4
Keywords: python grok,regex
Platform: UNKNOWN
